corfmann/__init__.py
corfmann/drf.py
corfmann/fields.py
corfmann/utils.py
corfmann/validators.py
Corfmann-0.0.2.dist-info/METADATA
Corfmann-0.0.2.dist-info/WHEEL
Corfmann-0.0.2.dist-info/top_level.txt
Corfmann-0.0.2.dist-info/RECORD
