Metadata-Version: 2.1
Name: Corfmann
Version: 0.0.2
Summary: Corfmann package
Home-page: https://gitlab.com/navasardyan.edgar/corfmann
Author: Edgar Navasardyan
Author-email: rips.arutyunyan@mail.com
License: UNKNOWN
Platform: UNKNOWN
